paddown.py
Paddown-0.1.0.dist-info/LICENSE
Paddown-0.1.0.dist-info/METADATA
Paddown-0.1.0.dist-info/WHEEL
Paddown-0.1.0.dist-info/entry_points.txt
Paddown-0.1.0.dist-info/top_level.txt
Paddown-0.1.0.dist-info/RECORD
