Metadata-Version: 2.1
Name: Paddown
Version: 0.1.0
Summary: CBC PKCS7 Padding Oracle Attack engine
Home-page: https://github.com/epadctf/Paddown
Author: EPAD
Author-email: epadctf@gmail.com
License: UNKNOWN
Platform: UNKNOWN
Classifier: Programming Language :: Python :: 3
Classifier: License :: OSI Approved :: MIT License
Classifier: Operating System :: OS Independent
Requires-Python: >=3.7
Requires-Dist: pycryptodome (==3.9.0)
